maue/__init__.py
maue/parser.py
maue_parser-0.1.1.dist-info/LICENSE
maue_parser-0.1.1.dist-info/METADATA
maue_parser-0.1.1.dist-info/WHEEL
maue_parser-0.1.1.dist-info/top_level.txt
maue_parser-0.1.1.dist-info/RECORD
