Metadata-Version: 2.1
Name: maue-parser
Version: 0.1.1
Summary: parser for maue files version 1.1
Home-page: https://github.com/code-and-fire/maue-parser
Author: Calvin Neumann
License: GNU Affero General Public License, Version 3
Platform: UNKNOWN
Classifier: Programming Language :: Python :: 3
License-File: LICENSE
